jupyterlab_celltagsclasses/__init__.py
jupyterlab_celltagsclasses/_version.py
jupyterlab_celltagsclasses-0.5.2.data/data/share/jupyter/labextensions/jupyterlab-celltagsclasses/build_log.json
jupyterlab_celltagsclasses-0.5.2.data/data/share/jupyter/labextensions/jupyterlab-celltagsclasses/package.json
jupyterlab_celltagsclasses-0.5.2.data/data/share/jupyter/labextensions/jupyterlab-celltagsclasses/static/lib_index_js.b6934364ccaf88932d03.js
jupyterlab_celltagsclasses-0.5.2.data/data/share/jupyter/labextensions/jupyterlab-celltagsclasses/static/lib_index_js.b6934364ccaf88932d03.js.map
jupyterlab_celltagsclasses-0.5.2.data/data/share/jupyter/labextensions/jupyterlab-celltagsclasses/static/remoteEntry.5c8e9d0343316652954c.js
jupyterlab_celltagsclasses-0.5.2.data/data/share/jupyter/labextensions/jupyterlab-celltagsclasses/static/remoteEntry.5c8e9d0343316652954c.js.map
jupyterlab_celltagsclasses-0.5.2.data/data/share/jupyter/labextensions/jupyterlab-celltagsclasses/static/style.js
jupyterlab_celltagsclasses-0.5.2.data/data/share/jupyter/labextensions/jupyterlab-celltagsclasses/static/style_index_js.07bc3c6f5582c5159c06.js
jupyterlab_celltagsclasses-0.5.2.data/data/share/jupyter/labextensions/jupyterlab-celltagsclasses/static/style_index_js.07bc3c6f5582c5159c06.js.map
jupyterlab_celltagsclasses-0.5.2.data/data/share/jupyter/labextensions/jupyterlab-celltagsclasses/install.json
jupyterlab_celltagsclasses-0.5.2.dist-info/METADATA
jupyterlab_celltagsclasses-0.5.2.dist-info/WHEEL
jupyterlab_celltagsclasses-0.5.2.dist-info/licenses/LICENSE
jupyterlab_celltagsclasses-0.5.2.dist-info/RECORD
