Metadata-Version: 2.3
Name: jupyterlab_celltagsclasses
Version: 0.5.2
Dynamic: Keywords
Summary: JLAB extension to add classes to cells based on their tags
Project-URL: Homepage, https://github.com/parmentelat/jupyterlab-celltagsclasses
Project-URL: Bug Tracker, https://github.com/parmentelat/jupyterlab-celltagsclasses/issues
Project-URL: Repository, https://github.com/parmentelat/jupyterlab-celltagsclasses.git
Author-email: Thierry Parmentelat <thierry.parmentelat@inria.fr>
License: BSD 3-Clause License
License-File: LICENSE
Classifier: Framework :: Jupyter
Classifier: Framework :: Jupyter :: JupyterLab
Classifier: Framework :: Jupyter :: JupyterLab :: 4
Classifier: Framework :: Jupyter :: JupyterLab :: Extensions
Classifier: Framework :: Jupyter :: JupyterLab :: Extensions :: Prebuilt
Classifier: License :: OSI Approved :: BSD License
Classifier: Programming Language :: Python
Classifier: Programming Language :: Python :: 3
Classifier: Programming Language :: Python :: 3.10
Classifier: Programming Language :: Python :: 3.11
Classifier: Programming Language :: Python :: 3.12
Requires-Python: >=3.8
